gitbrew/Readme.md
gitbrew/__init__.py
gitbrew/command_handler.py
gitbrew/constants.py
gitbrew/exceptions.py
gitbrew/generate_readme.py
gitbrew/gitpy.py
gitbrew/issue_manager.py
gitbrew/llms/__init__.py
gitbrew/llms/cohere.py
gitbrew/llms/openai.py
gitbrew/main.py
gitbrew/prompts/__init__.py
gitbrew/prompts/clarification_prompt.py
gitbrew/prompts/explain_command_prompt.py
gitbrew/prompts/find_similar_issues_prompt.py
gitbrew/prompts/generate_command_prompt.py
gitbrew/prompts/generate_readme_prompt.py
gitbrew/prompts/pull_request_review_prompt.py
gitbrew/prompts/summarize_file_prompt.py
gitbrew/pull_requests.py
gitbrew/questions.py
gitbrew/shell.py
gitbrew/utilities.py
gitbrew-0.2.5.dist-info/METADATA
gitbrew-0.2.5.dist-info/WHEEL
gitbrew-0.2.5.dist-info/entry_points.txt
gitbrew-0.2.5.dist-info/RECORD
