Metadata-Version: 2.1
Name: gitbrew
Version: 0.2.5
Summary: LLM-powered github utility
License: MIT
Author: Navneet Desai
Author-email: navneetdesai44@gmail.com
Requires-Python: >=3.9,<4.0
Classifier: License :: OSI Approved :: MIT License
Classifier: Programming Language :: Python :: 3
Classifier: Programming Language :: Python :: 3.9
Classifier: Programming Language :: Python :: 3.10
Classifier: Programming Language :: Python :: 3.11
Requires-Dist: black (>=23.7.0,<24.0.0)
Requires-Dist: bs4 (>=0.0.1,<0.0.2)
Requires-Dist: chromadb (>=0.4.11,<0.5.0)
Requires-Dist: cohere (>=4.27,<5.0)
Requires-Dist: gensim (>=4.3.2,<5.0.0)
Requires-Dist: isort (>=5.12.0,<6.0.0)
Requires-Dist: openai (>=0.28.0,<0.29.0)
Requires-Dist: pinecone-client (>=2.2.4,<3.0.0)
Requires-Dist: pre-commit (>=3.3.3,<4.0.0)
Requires-Dist: pygithub (>=1.59.1,<2.0.0)
Requires-Dist: pyinquirer (>=1.0.3,<2.0.0)
Requires-Dist: pytest (>=7.4.0,<8.0.0)
Requires-Dist: python-dotenv (>=1.0.0,<2.0.0)
Requires-Dist: rich (>=13.6.0,<14.0.0)
Requires-Dist: scikit-learn (>=1.3.1,<2.0.0)
Requires-Dist: tabulate (>=0.9.0,<0.10.0)
Requires-Dist: tiktoken (>=0.5.1,<0.6.0)
